neweraai/__garbage__.py
neweraai/__init__.py
neweraai/modules/__init__.py
neweraai/modules/core/__init__.py
neweraai/modules/core/core.py
neweraai/modules/core/exceptions.py
neweraai/modules/core/language.py
neweraai/modules/core/messages.py
neweraai/modules/core/settings.py
neweraai/modules/lab/__init__.py
neweraai/modules/lab/audio.py
neweraai/modules/lab/build.py
neweraai/modules/lab/download.py
neweraai/modules/lab/speech.py
neweraai/modules/lab/statistics.py
neweraai/modules/lab/unzip.py
neweraai/modules/locales/en/LC_MESSAGES/base.mo
neweraai/modules/locales/ru/LC_MESSAGES/base.mo
neweraai-1.0.4.dist-info/LICENSE
neweraai-1.0.4.dist-info/METADATA
neweraai-1.0.4.dist-info/WHEEL
neweraai-1.0.4.dist-info/entry_points.txt
neweraai-1.0.4.dist-info/top_level.txt
neweraai-1.0.4.dist-info/RECORD
